Trolltext/__init__.py
Trolltext/allfont.py
Trolltext/mock_text.py
Trolltext/style_text.py
trolltext-0.1.2.dist-info/METADATA
trolltext-0.1.2.dist-info/WHEEL
trolltext-0.1.2.dist-info/top_level.txt
trolltext-0.1.2.dist-info/RECORD
