Metadata-Version: 2.4
Name: trolltext
Version: 0.1.2
Summary: Текстовые стили с множеством шрифтов
Home-page: https://github.com/G3tfun/trolltext
Author: G3tfun
Author-email: no-reply@example.com
Classifier: Programming Language :: Python :: 3
Classifier: Operating System :: OS Independent
Requires-Python: >=3.6
Dynamic: author
Dynamic: author-email
Dynamic: classifier
Dynamic: description
Dynamic: description-content-type
Dynamic: home-page
Dynamic: requires-python
Dynamic: summary
